chinstrap/__init__.py
chinstrap/version.py
chinstrap/compiler/__init__.py
chinstrap/core/__init__.py
chinstrap/core/config.py
chinstrap/core/create.py
chinstrap/core/debugger.py
chinstrap/core/initialize.py
chinstrap/core/templates.py
chinstrap/core/sources/chinstrap-config.yml
chinstrap/core/sources/contracts/FA1.2.py
chinstrap/core/sources/contracts/SampleContract.py
chinstrap/core/sources/originations/1_FA12_origination.py
chinstrap/core/sources/originations/1_samplecontract_origination.py
chinstrap/core/sources/tests/FA1.2.smartpy.py
chinstrap/core/sources/tests/sampleContractSmartPy.py
chinstrap/core/sources/tests/samplecontractPytest.py
chinstrap/helpers/__init__.py
chinstrap/helpers/container.py
chinstrap/languages/__init__.py
chinstrap/languages/ligo.py
chinstrap/languages/smartpy.py
chinstrap/originations/__init__.py
chinstrap/repl/__init__.py
chinstrap/repl/repl.py
chinstrap/sandbox/__init__.py
chinstrap/tests/__init__.py
chinstrap-1.1.6.data/scripts/chinstrap
chinstrap-1.1.6.dist-info/LICENSE
chinstrap-1.1.6.dist-info/METADATA
chinstrap-1.1.6.dist-info/WHEEL
chinstrap-1.1.6.dist-info/top_level.txt
chinstrap-1.1.6.dist-info/RECORD
