Metadata-Version: 2.1
Name: chinstrap
Version: 1.1.6
Summary: A swiss-army-knife for Tezos Smart Contract developers
Home-page: https://github.com/ant4g0nist/chinstrap
Author: ant4g0nist
Author-email: me@chinstrap.io
License: MIT License
Classifier: Environment :: Console
Classifier: Intended Audience :: Developers
Classifier: Programming Language :: Python :: 3.7
Classifier: Programming Language :: Python :: 3.8
Classifier: Programming Language :: Python :: 3.9
Classifier: Topic :: Software Development :: Build Tools
Requires-Python: >=3.7
License-File: LICENSE
Requires-Dist: requests (>=2.27.1)
Requires-Dist: docker (>=5.0.3)
Requires-Dist: pytest (>=6.2.5)
Requires-Dist: ptpython (>=3.0.20)
Requires-Dist: pytezos (>=3.6.0)
Requires-Dist: halo (>=0.0.31)
Requires-Dist: python-gitlab (>=3.1.0)
Requires-Dist: rich (>=11.0.0)
Requires-Dist: pre-commit (>=2.17.0)
